{
  "slug": "nerf-vague-glycemie",
  "title": "Comment le Nerf Vague Peut Ameliorer le Controle de la Glycemie",
  "excerpt": "Decouvrez comment le nerf vague influence le controle du glucose, la sensibilite a l'insuline et l'inflammation - plus des moyens concrets pour le soutenir et ameliorer votre sante metabolique.",
  "content": "# Comment le Nerf Vague Peut Ameliorer le Controle de la Glycemie\n\n## Introduction\n\nDecouvrez comment le nerf vague influence le controle du glucose, la sensibilite a l'insuline et l'inflammation - plus des moyens concrets pour le soutenir et ameliorer votre sante metabolique.\n\n## Votre metabolisme fonctionne sur des signaux de votre cerveau\n\nLe nerf vague est le dixieme nerf cranien. Il commence dans votre tronc cerebral et s'etend jusqu'au coeur, aux poumons, au foie, au pancreas, aux intestins et plus encore.\n\n**80% de ses fibres envoient des informations de votre corps vers votre cerveau** (afferentes). Les autres 20% delivrent des instructions du cerveau vers le corps (efferentes).\n\nEt il joue des roles cles dans l'intestin, le pancreas et le foie.\n\n- **Dans l'intestin**, il aide a reguler la satiete et l'appetit\n- **Dans le pancreas**, il soutient la liberation d'insuline apres les repas\n- **Dans le foie**, il aide a coordonner le stockage et la production de glucose\n\nLorsque le tonus vagal est fort, ces systemes communiquent efficacement. La glycemie reste stable. L'utilisation de l'energie est equilibree.\n\n## Stimuler le nerf vague peut ameliorer le controle du glucose\n\nSi votre nerf vague ne fonctionne pas bien, vos tissus peuvent devenir moins reactifs a l'insuline. C'est ce qu'on appelle la **resistance a l'insuline**, un moteur cle du dysfonctionnement metabolique.\n\nDes etudes animales ont montre que stimuler le nerf vague peut **restaurer la sensibilite a l'insuline et ameliorer l'absorption du glucose** dans les muscles et le foie, meme sans perte de poids majeure.\n\nCela suggere qu'ameliorer le tonus vagal pourrait aider votre corps a utiliser l'insuline plus efficacement - un gros avantage si vous essayez de prevenir ou de gerer le diabete de type 2.\n\n## Pourquoi le tonus vagal et la VFC affectent le controle du glucose\n\nLe stress chronique stimule votre systeme nerveux sympathique (mode combat ou fuite) et pousse votre corps vers l'inflammation et le stockage des graisses. Si votre tonus vagal est bas, vous ne pouvez pas facilement revenir en mode repos et digestion.\n\nCela peut conduire a :\n\n- Un mauvais controle du glucose\n- Une augmentation de la graisse viscerale\n- Un cortisol eleve\n\nLa VFC (Variabilite de la Frequence Cardiaque) est souvent plus basse chez les personnes avec resistance a l'insuline et diabete de type 2. Ce n'est pas une coincidence. Un nerf vague plus reactif = un meilleur controle metabolique.\n\n## Comment stimuler le nerf vague\n\nVous n'avez pas besoin d'appareils couteux ou d'interventions cliniques pour soutenir votre nerf vague. Il existe des moyens simples et prouves pour le stimuler qui peuvent ameliorer le controle du glucose, reduire l'inflammation et ameliorer la flexibilite metabolique. Voici les strategies les plus efficaces, basees sur la science.\n\n### 1. Respiration de resonance\n\n- **Ce que c'est :** Respiration lente et profonde a un rythme de 4,5 a 6 respirations par minute\n- **Pourquoi ca marche :** Active les barorecepteurs qui ameliorent le tonus vagal et ameliorent la variabilite de la frequence cardiaque\n- **Comment faire :** Inspirez pendant 5 secondes, expirez pendant 5 secondes. Repetez pendant 5-10 minutes quotidiennement\n\n### 2. Exposition au froid\n\n- **Ce que c'est :** Exposition au froid sur le visage ou le cou, ou douches froides corps entier\n- **Pourquoi ca marche :** Stimule le reflexe de plongee des mammiferes, augmentant l'activite parasympathique\n- **Comment faire :** Eclaboussez de l'eau froide sur votre visage ou terminez votre douche avec 30-60 secondes d'eau froide\n\n### 3. Fredonnement\n\n- **Ce que c'est :** Fredonner, chanter, se gargariser\n- **Pourquoi ca marche :** Engage les muscles connectes au nerf vague, surtout dans la gorge et les cordes vocales\n- **Comment faire :** Fredonnez ou gargarisez-vous bruyamment pendant 30 secondes quotidiennement. Chanter marche aussi\n\n### 4. Mangez des probiotiques\n\n- **Ce que c'est :** Aliments qui soutiennent les bacteries intestinales, comme le yaourt, le kefir, la choucroute, l'ail et l'avoine\n- **Pourquoi ca marche :** Un intestin sain ameliore la signalisation du nerf vague via l'axe intestin-cerveau\n\n### 5. Dormez bien et reposez-vous\n\n- **Ce que c'est :** Sommeil constant, gestion du stress et temps pour la recuperation\n- **Pourquoi ca marche :** Un mauvais sommeil et le stress chronique suppriment le tonus vagal et favorisent l'inflammation\n- **Comment faire :** Visez 7-9 heures de sommeil de qualite. Evitez les ecrans et les repas lourds avant le coucher\n\nCes strategies peuvent sembler simples, mais elles entrainent le nerf vague de maniere constante au fil du temps - et c'est cette constance qui aide a faire passer votre systeme metabolique de reactif a resilient.\n\n## Resume\n\nIl existe des preuves solides que le nerf vague a une influence sur la facon dont nos corps traitent la nourriture pour l'energie, et nos niveaux de glycemie.\n\nSi vous voulez une meilleure sante metabolique, un meilleur controle du glucose et plus d'equilibre energetique, soutenir votre nerf vague, combine avec l'alimentation, l'exercice et de bonnes habitudes metaboliques, pourrait etre un outil important pour gerer le glucose et maintenir un poids sain.\n\n---\n\n## Pret a optimiser votre metabolisme ?\n\nDecouvrez nos formules de coaching personnalise pour transformer votre sante metabolique.\n\n[Decouvrir le coaching ACHZOD](https://www.achzodcoaching.com/formules-coaching)",
  "category": "metabolisme",
  "author": "ACHZOD",
  "date": "2026-01-09",
  "readTime": "5 min",
  "image": "https://images.unsplash.com/photo-1544367567-0f2fcb009e0b?w=1200",
  "sourceUrl": "https://blog.ultrahuman.com/blog/vagus-nerve-why-its-important-how-it-works/",
  "charCount": 5124
}
